calaccess_scraped/__init__.py
calaccess_scraped/apps.py
calaccess_scraped/admin/__init__.py
calaccess_scraped/admin/base.py
calaccess_scraped/admin/candidates.py
calaccess_scraped/admin/incumbents.py
calaccess_scraped/admin/propositions.py
calaccess_scraped/admin/tracking.py
calaccess_scraped/data/CandidateElectionItem.csv
calaccess_scraped/data/CandidateItem.csv
calaccess_scraped/data/IncumbentElectionItem.csv
calaccess_scraped/data/IncumbentItem.csv
calaccess_scraped/data/PropositionCommitteeItem.csv
calaccess_scraped/data/PropositionElectionItem.csv
calaccess_scraped/data/PropositionItem.csv
calaccess_scraped/html/candidates/1.html
calaccess_scraped/html/candidates/10.html
calaccess_scraped/html/candidates/100.html
calaccess_scraped/html/candidates/101.html
calaccess_scraped/html/candidates/106.html
calaccess_scraped/html/candidates/11.html
calaccess_scraped/html/candidates/122.html
calaccess_scraped/html/candidates/123.html
calaccess_scraped/html/candidates/124.html
calaccess_scraped/html/candidates/125.html
calaccess_scraped/html/candidates/127.html
calaccess_scraped/html/candidates/13.html
calaccess_scraped/html/candidates/132.html
calaccess_scraped/html/candidates/133.html
calaccess_scraped/html/candidates/134.html
calaccess_scraped/html/candidates/138.html
calaccess_scraped/html/candidates/139.html
calaccess_scraped/html/candidates/14.html
calaccess_scraped/html/candidates/140.html
calaccess_scraped/html/candidates/141.html
calaccess_scraped/html/candidates/143.html
calaccess_scraped/html/candidates/144.html
calaccess_scraped/html/candidates/145.html
calaccess_scraped/html/candidates/146.html
calaccess_scraped/html/candidates/15.html
calaccess_scraped/html/candidates/154.html
calaccess_scraped/html/candidates/155.html
calaccess_scraped/html/candidates/156.html
calaccess_scraped/html/candidates/157.html
calaccess_scraped/html/candidates/16.html
calaccess_scraped/html/candidates/160.html
calaccess_scraped/html/candidates/161.html
django_calaccess_scraped_data-3.4.0.dist-info/LICENSE
django_calaccess_scraped_data-3.4.0.dist-info/METADATA
django_calaccess_scraped_data-3.4.0.dist-info/WHEEL
django_calaccess_scraped_data-3.4.0.dist-info/top_level.txt
django_calaccess_scraped_data-3.4.0.dist-info/RECORD
